Metadata-Version: 2.1
Name: deep-replacer
Version: 0.0.5
Summary: Given a list, set, tuple or dictionary as data input, loop through the data and replace all values that are not a list, set, tuple or dictionary using a replace function.
Home-page: https://github.com/zaironjacobs/deep-replacer
Download-URL: https://github.com/zaironjacobs/deep-replacer/archive/v0.0.5.tar.gz
Author: Zairon Jacobs
Author-email: zaironjacobs@gmail.com
License: MIT
Keywords: replace,replacer,deep
Classifier: Development Status :: 5 - Production/Stable
Classifier: Intended Audience :: Developers
Classifier: License :: OSI Approved :: MIT License
Classifier: Operating System :: OS Independent
Classifier: Programming Language :: Python :: 3.10
Classifier: Natural Language :: English
Requires-Python: >=3
License-File: LICENSE
